{
  "time": 1553111301819,
  "a": {
    "id": 1314151403,
    "attr": {
      "vehicle_luggage_capacity": "455",
      "vehicle_transmission": "Manual",
      "vehicle_model": "A5",
      "vehicle_original_number_plate": "false",
      "vehicle_registration_year": "2013",
      "vehicle_not_exported": "true",
      "vehicle_road_worthy": "true",
      "vehicle_euro_emission": "Euro 6",
      "vehicle_insurance_group": "27E",
      "vehicle_not_stolen": "true",
      "vehicle_colour": "White",
      "vehicle_engine_size": "1798",
      "vehicle_doors": "2",
      "vehicle_uk_model": "true",
      "vehicle_seats": "4",
      "price": "1575000",
      "vehicle_average_mpg": "49.6",
      "seller_type": "Trade",
      "vehicle_body_type": "Coupe",
      "vehicle_urban_mpg": "38.2",
      "vehicle_estimated_mileage": "28621",
      "vehicle_top_speed": "143",
      "vehicle_fuel_type": "Petrol",
      "vehicle_engine_power": "167.6",
      "vehicle_make": "Audi",
      "vehicle_extra_urban_mpg": "58.9",
      "vehicle_brochure_engine_size": "1.8",
      "vehicle_fuel_capacity": "63",
      "vehicle_cap_code": "AUA518BLK2CPTM 1",
      "vehicle_original_colour": "true",
      "vehicle_derivative": "Black Edition",
      "vrn": "SL63EWR",
      "vehicle_not_scrapped": "true",
      "vehicle_not_writeoff": "true",
      "vehicle_vhc_checked": "true",
      "vehicle_mileage": "21217",
      "vehicle_previous_keepers": "1",
      "vehicle_acceleration_0_62": "7.9",
      "vehicle_emission": "134"
    },
    "u": {
      "hue": "qgZGxt8BJggx3Cj9IDQAmu+yMoIn6zHKaEbn9tQFCrMtNOe16Y3Km6I2/0NQoyFpSXnM6mCAmbwZ7V3a2ncuvA==",
      "haid": "85d6c8e24f6b17e0c1cd2f4b79022019",
      "at": "Pro",
      "scr": 0.0,
      "rc": 0,
      "rr": 23,
      "rs": 711
    },
    "cdt": 1537191965577,
    "lpdt": 1552768863182,
    "dl": 2273,
    "ic": 20,
    "vc": 0,
    "r2sURL": false,
    "ftr": [ "WEBSITE_URL" ],
    "prc": {
      "amt": 1575000,
      "cur": "GBP"
    },
    "acs": "other"
  },
  "l": {
    "c": { "id": 24016 },
    "l0": { "id": 10000392 },
    "l1": { "id": 10000395 },
    "l2": { "id": 10000349 },
    "l3": { "id": 24016 },
    "ltlng": "55.9037;-4.22578",
    "pcid": "G642AB"
  },
  "c": {
    "c": { "id": 10302 },
    "l0": { "id": 1 },
    "l1": { "id": 2551 },
    "l2": { "id": 9311 },
    "l3": { "id": 10302 }
  },
  "p": {
    "t": "VIP",
    "pl": "responsive"
  },
  "u": {
    "huid": "317b159fcc36e54b2b8212aa74f8d988",
    "hue": "3J5EF5Z6OWCYk8cEaQANlxU77o2TkxbPicHkyXceYFeRsCXWQvn4psQbfY9XN7y36/M5LTGvCODRKuMOqDbaYw==",
    "at": "Standard",
    "li": true,
    "tg": {
      "stg": "",
      "ptg": "GTALL-15065-30-B;TREEBAY_ON_BROWSE-V1"
    }
  },
  "d": {
    "s_ck": "mztlvsbw5nwd1nxffx77oqea9",
    "t": "d",
    "ck": "8c5045c7-d492-4bc3-a8a1-ccea0a04a88e"
  },
  "name": "VipViewEvent"
}
